setup.py
github_watchdog/__init__.py
github_watchdog.egg-info/PKG-INFO
github_watchdog.egg-info/SOURCES.txt
github_watchdog.egg-info/dependency_links.txt
github_watchdog.egg-info/not-zip-safe
github_watchdog.egg-info/top_level.txt