Metadata-Version: 1.0
Name: github-watchdog
Version: 0.1
Summary: monitor the contributors on an open github project
Home-page: UNKNOWN
Author: Srikanth Pothedar
Author-email: srikanth.pothedar@gmail.com
License: MIT
Platform: UNKNOWN
